{
  "$schema": "https://developer.microsoft.com/json-schemas/fabric/item/report/definition/visualContainer/2.5.0/schema.json",
  "name": "54a0c01e7cdaaee02c8d",
  "position": {
    "x": 379.07828351916044,
    "y": 95.5974886197713,
    "z": 5000,
    "height": 38.718861209964409,
    "width": 60.355871886120994,
    "tabOrder": -1001
  },
  "visual": {
    "visualType": "image",
    "objects": {
      "image": [
        {
          "properties": {
            "sourceType": {
              "expr": {
                "Literal": {
                  "Value": "'imageData'"
                }
              }
            },
            "sourceField": {
              "expr": {
                "Measure": {
                  "Expression": {
                    "SourceRef": {
                      "Entity": "City Metrics"
                    }
                  },
                  "Property": "Briarport Medal"
                }
              }
            }
          }
        }
      ]
    },
    "visualContainerObjects": {
      "title": [
        {
          "properties": {
            "text": {
              "expr": {
                "Literal": {
                  "Value": "'Briarport Crown'"
                }
              }
            }
          }
        }
      ]
    },
    "drillFilterOtherVisuals": true
  },
  "parentGroupName": "26b45de60be930db651a"
}